taskbee/__init__.py
taskbee/taskbee.py
taskbee-0.0.1.dist-info/METADATA
taskbee-0.0.1.dist-info/WHEEL
taskbee-0.0.1.dist-info/entry_points.txt
taskbee-0.0.1.dist-info/licenses/LICENSE
taskbee-0.0.1.dist-info/RECORD
