Metadata-Version: 2.1
Name: TaskBee
Version: 0.0.1
Summary: A command orchestration tool
Project-URL: Homepage, https://github.com/MQ-xz/TaskBee
Project-URL: Issues, https://github.com/MQ-xz/TaskBee/issues
Author-email: Mahshooq Zubair <kmahshooq@gmail.com>
License-File: LICENSE
Classifier: License :: OSI Approved :: MIT License
Classifier: Operating System :: OS Independent
Classifier: Programming Language :: Python :: 3
Requires-Python: >=3.8
